resource_graph/__init__.py
resource_graph/config.py
resource_graph/extension.py
resource_graph/scan_resource.py
resource_graph/altimeter/__init__.py
resource_graph/altimeter/aws/__init__.py
resource_graph/altimeter/aws/aws2n.py
resource_graph/altimeter/aws/log_events.py
resource_graph/altimeter/aws/resource_service_region_mapping.py
resource_graph/altimeter/aws/settings.py
resource_graph/altimeter/aws/auth/__init__.py
resource_graph/altimeter/aws/auth/accessor.py
resource_graph/altimeter/aws/auth/cache.py
resource_graph/altimeter/aws/auth/exceptions.py
resource_graph/altimeter/aws/auth/multi_hop_accessor.py
resource_graph/altimeter/aws/resource/__init__.py
resource_graph/altimeter/aws/resource/account.py
resource_graph/altimeter/aws/resource/resource_spec.py
resource_graph/altimeter/aws/resource/unscanned_account.py
resource_graph/altimeter/aws/resource/util.py
resource_graph/altimeter/aws/resource/acm/__init__.py
resource_graph/altimeter/aws/resource/acm/certificate.py
resource_graph/altimeter/aws/resource/awslambda/__init__.py
resource_graph/altimeter/aws/resource/awslambda/function.py
resource_graph/altimeter/aws/resource/cloudtrail/__init__.py
resource_graph/altimeter/aws/resource/cloudtrail/trail.py
resource_graph/altimeter/aws/resource/cloudwatch/__init__.py
resource_graph/altimeter/aws/resource/cloudwatch/metric.py
resource_graph/altimeter/aws/resource/cognito_identity/__init__.py
resource_graph/altimeter/aws/resource/cognito_identity/identity_pool.py
resource_graph/altimeter/aws/resource/cognito_idp/__init__.py
resource_graph/altimeter/aws/resource/cognito_idp/group.py
resource_graph/altimeter/aws/resource/cognito_idp/user.py
resource_graph/altimeter/aws/resource/cognito_idp/user_pools.py
resource_graph/altimeter/aws/resource/dynamodb/__init__.py
resource_graph/altimeter/aws/resource/dynamodb/dynamodb_table.py
resource_graph/altimeter/aws/resource/ec2/__init__.py
resource_graph/altimeter/aws/resource/ec2/flow_log.py
localstack_extension_resource_graph-0.2.0.post3.dist-info/METADATA
localstack_extension_resource_graph-0.2.0.post3.dist-info/WHEEL
localstack_extension_resource_graph-0.2.0.post3.dist-info/entry_points.txt
localstack_extension_resource_graph-0.2.0.post3.dist-info/top_level.txt
localstack_extension_resource_graph-0.2.0.post3.dist-info/RECORD
